README.rst
setup.cfg
setup.py
django_stored_settings.egg-info/PKG-INFO
django_stored_settings.egg-info/SOURCES.txt
django_stored_settings.egg-info/dependency_links.txt
django_stored_settings.egg-info/top_level.txt
stored_settings/__init__.py
stored_settings/admin.py
stored_settings/context_processors.py
stored_settings/forms.py
stored_settings/models.py
stored_settings/settings.py
stored_settings/templates/admin/stored_settings/settings/create_form.html