Metadata-Version: 1.1
Name: django-stored-settings
Version: 0.2.0
Summary: Module allowing dynamically to create and further on to edit via django-admin settings
Home-page: https://github.com/zvadim/django-stored-settings
Author: Vadym Zabiiaka
Author-email: v.zabiiaka@gmail.com
License: MIT license
Download-URL: https://github.com/zvadim/django-stored-settings/tarball/0.2.0
Keywords: django,settings,dynamic,stored
Platform: UNKNOWN
Classifier: Environment :: Web Environment
Classifier: Intended Audience :: Developers
Classifier: License :: OSI Approved :: MIT License
Classifier: Programming Language :: Python
Classifier: Framework :: Django
Classifier: Topic :: Software Development :: Libraries :: Python Modules
Requires: django (>=1.3)
Requires: Pillow
